odoo/addons/base_bank_from_iban/README.rst
odoo/addons/base_bank_from_iban/__init__.py
odoo/addons/base_bank_from_iban/__manifest__.py
odoo/addons/base_bank_from_iban/i18n/base_bank_from_iban.pot
odoo/addons/base_bank_from_iban/i18n/nl.po
odoo/addons/base_bank_from_iban/models/__init__.py
odoo/addons/base_bank_from_iban/models/account_journal.py
odoo/addons/base_bank_from_iban/models/res_bank.py
odoo/addons/base_bank_from_iban/models/res_partner_bank.py
odoo/addons/base_bank_from_iban/readme/CONFIGURE.rst
odoo/addons/base_bank_from_iban/readme/CONTRIBUTORS.rst
odoo/addons/base_bank_from_iban/readme/DESCRIPTION.rst
odoo/addons/base_bank_from_iban/readme/USAGE.rst
odoo/addons/base_bank_from_iban/static/description/icon.png
odoo/addons/base_bank_from_iban/static/description/index.html
odoo/addons/base_bank_from_iban/tests/__init__.py
odoo/addons/base_bank_from_iban/tests/test_base_bank_from_iban.py
odoo/addons/base_bank_from_iban/views/res_bank_view.xml
odoo13_addon_base_bank_from_iban-13.0.1.0.1.dist-info/METADATA
odoo13_addon_base_bank_from_iban-13.0.1.0.1.dist-info/WHEEL
odoo13_addon_base_bank_from_iban-13.0.1.0.1.dist-info/top_level.txt
odoo13_addon_base_bank_from_iban-13.0.1.0.1.dist-info/RECORD
